startcp/__init__.py
startcp/__main__.py
startcp/builder.py
startcp/codechef.py
startcp/codeforces.py
startcp/constants.py
startcp/functions.py
startcp/logger.py
startcp/printer.py
startcp/utilities.py
startcp/version.py
startcp_cli-1.0.3.dist-info/LICENSE
startcp_cli-1.0.3.dist-info/METADATA
startcp_cli-1.0.3.dist-info/WHEEL
startcp_cli-1.0.3.dist-info/entry_points.txt
startcp_cli-1.0.3.dist-info/top_level.txt
startcp_cli-1.0.3.dist-info/RECORD
