Metadata-Version: 2.1
Name: startcp-cli
Version: 1.0.3
Summary: A CLI boiler plate for current competition.
Home-page: https://github.com/asprazz/startcp-cli
Author: Sujit and Ankush
Author-email: ankushpatil6174@gmail.com
License: UNKNOWN
Platform: UNKNOWN
Requires-Python: >=3.6
License-File: LICENSE
Requires-Dist: requests (>=2.23)
Requires-Dist: argparse
Requires-Dist: colorama
Requires-Dist: python-dotenv
Requires-Dist: Rangebi
Requires-Dist: beautifulsoup4 (==4.10.0)
Requires-Dist: halo (==0.0.31)
